{"ModeloBase": "ALEXNet", "fecha": "17-03-2025_17.57", "NombreModelo": "AlexNet_17-03-2025_17.57", "PesosModelo": "AlexNet.pth", "mini_batch_size": 64, "max_epochs": 1, "learn_rate": 0.5, "optimizer": "Adam", "test_loss": 4.3845570104342707e+18, "test_accuracy": 0.5, "metricas": {"VP": 40, "FN": 0, "VN": 0, "FP": 40, "fake": {"F1": 0.0, "precision": 0.0, "recall": 0.0}, "real": {"F1": 0.6666666621111113, "precision": 0.49999999993750005, "recall": 0.99999999975}}, "history": {"loss": [5.846076013912361e+17], "accuracy": [0.5031982942430704], "val_accuracy": [0.5], "val_loss": [17048930353152.0]}}